tubbe/__init__.py
tubbe/circuit_breaker.py
tubbe/command.py
tubbe/exceptions.py
tubbe/metrics.py
tubbe-0.6.0.dist-info/DESCRIPTION.rst
tubbe-0.6.0.dist-info/METADATA
tubbe-0.6.0.dist-info/RECORD
tubbe-0.6.0.dist-info/WHEEL
tubbe-0.6.0.dist-info/entry_points.txt
tubbe-0.6.0.dist-info/metadata.json
tubbe-0.6.0.dist-info/top_level.txt
