Metadata-Version: 2.0
Name: tubbe
Version: 0.6.0
Summary: A failure-tolerant library for fallback acquired module.
Home-page: UNKNOWN
Author: torpedoallen
Author-email: torpedoallen@gmail.com
License: UNKNOWN
Keywords: failure-tolerant fallback
Platform: UNKNOWN
Requires-Dist: gevent (>=1.2.2)
Requires-Dist: six
